telefonia/__init__.py
telefonia/main.py
telefonia-0.1.0.dist-info/WHEEL
telefonia-0.1.0.dist-info/METADATA
telefonia-0.1.0.dist-info/RECORD
