Metadata-Version: 2.1
Name: telefonia
Version: 0.1.0
Summary: 
Author: Bamatailo
Author-email: 103551990+Bamatailo@users.noreply.github.com
Requires-Python: >=3.9,<4.0
Classifier: Programming Language :: Python :: 3
Classifier: Programming Language :: Python :: 3.10
Classifier: Programming Language :: Python :: 3.9
Requires-Dist: numpy (>=1.23.0,<2.0.0)
